meshagent/openai/__init__.py
meshagent/openai/version.py
meshagent/openai/proxy/__init__.py
meshagent/openai/proxy/proxy.py
meshagent/openai/tools/__init__.py
meshagent/openai/tools/apply_patch.py
meshagent/openai/tools/completions_adapter.py
meshagent/openai/tools/responses_adapter.py
meshagent/openai/tools/schema.py
meshagent/openai/tools/stt.py
meshagent/openai/tools/stt_test.py
meshagent_openai-0.25.1.dist-info/licenses/LICENSE
meshagent_openai-0.25.1.dist-info/METADATA
meshagent_openai-0.25.1.dist-info/WHEEL
meshagent_openai-0.25.1.dist-info/top_level.txt
meshagent_openai-0.25.1.dist-info/RECORD
